predictive_imputer/__init__.py
predictive_imputer/predictive_imputer.py
predictive_imputer-0.2.0.dist-info/DESCRIPTION.rst
predictive_imputer-0.2.0.dist-info/METADATA
predictive_imputer-0.2.0.dist-info/RECORD
predictive_imputer-0.2.0.dist-info/WHEEL
predictive_imputer-0.2.0.dist-info/metadata.json
predictive_imputer-0.2.0.dist-info/top_level.txt
