Metadata-Version: 2.0
Name: predictive-imputer
Version: 0.2.0
Summary: Predictive imputation of missing values with sklearn interface. This is a simple implementation of the idea presented in the MissForest R package.
Home-page: https://github.com/log0ymxm/predictive_imputer
Author: Paul English
Author-email: paulnglsh@gmail.com
License: MIT license
Keywords: predictive_imputer
Platform: UNKNOWN
Classifier: Development Status :: 2 - Pre-Alpha
Classifier: Intended Audience :: Developers
Classifier: License :: OSI Approved :: MIT License
Classifier: Natural Language :: English
Classifier: Programming Language :: Python :: 2
Classifier: Programming Language :: Python :: 2.6
Classifier: Programming Language :: Python :: 2.7
Classifier: Programming Language :: Python :: 3
Classifier: Programming Language :: Python :: 3.3
Classifier: Programming Language :: Python :: 3.4
Classifier: Programming Language :: Python :: 3.5
Requires-Dist: scikit-learn
